<?xml version="1.0"?>
<psalm
    errorLevel="1"
    resolveFromConfigFile="true"
    xmlns:xsi="http://www.w3.org/2001/XMLSchema-instance"
    xmlns="https://getpsalm.org/schema/config"
    xsi:schemaLocation="https://getpsalm.org/schema/config vendor/vimeo/psalm/config.xsd"
    findUnusedBaselineEntry="true"
    findUnusedCode="true"
>
    <projectFiles>
        <directory name="bin" />
        <directory name="config/php-utils/^1.7.0" />
        <directory name="public" />
        <directory name="src" />
        <ignoreFiles>
            <directory name="vendor" />
        </ignoreFiles>
    </projectFiles>
</psalm>
